ipymario/__init__.py
ipymario/static/widget.css
ipymario/static/widget.js
ipymario-0.1.0.dist-info/METADATA
ipymario-0.1.0.dist-info/WHEEL
ipymario-0.1.0.dist-info/licenses/LICENSE
ipymario-0.1.0.dist-info/RECORD
