Metadata-Version: 2.3
Name: ipymario
Version: 0.1.0
License: MIT
License-File: LICENSE
Requires-Dist: anywidget
Requires-Dist: numpy
Provides-Extra: dev
Requires-Dist: jupyterlab; extra == 'dev'
Requires-Dist: watchfiles; extra == 'dev'
